ccfwidget/__init__.py
ccfwidget/allen_id_label.py
ccfwidget/ipytree_widget.py
ccfwidget/structure_graph.py
ccfwidget/structure_mesh.py
ccfwidget/swc_morphology.py
ccfwidget/treemap_widget.py
ccfwidget/widget_ccf.py
ccfwidget-0.5.3.dist-info/LICENSE.txt
ccfwidget-0.5.3.dist-info/WHEEL
ccfwidget-0.5.3.dist-info/METADATA
ccfwidget-0.5.3.dist-info/RECORD
